LICENSE.txt
MANIFEST.in
README.rst
setup.py
solrcloudpy/__init__.py
solrcloudpy/connection.py
solrcloudpy/parameters.py
solrcloudpy/utils.py
solrcloudpy.egg-info/PKG-INFO
solrcloudpy.egg-info/SOURCES.txt
solrcloudpy.egg-info/dependency_links.txt
solrcloudpy.egg-info/requires.txt
solrcloudpy.egg-info/top_level.txt
solrcloudpy/collection/__init__.py
solrcloudpy/collection/admin.py
solrcloudpy/collection/indexer.py
solrcloudpy/collection/schema.py
solrcloudpy/collection/search.py
solrcloudpy/collection/stats.py
test/test_collection.py
test/test_connection.py
test/test_search.py