Metadata-Version: 1.1
Name: solrcloudpy
Version: 4.0.1
Summary: python library for interacting with SolrCloud 
Home-page: https://github.com/solrcloudpy/solrcloudpy
Author: Didier Deshommes, Robert Elwell
Author-email: dfdeshom@gmail.com, robert.elwell@gmail.com
License: LICENSE.txt
Keywords: solr solrcloud
Platform: any
Classifier: Development Status :: 3 - Alpha
Classifier: Intended Audience :: Developers
Classifier: License :: OSI Approved :: BSD License
Classifier: Operating System :: OS Independent
Classifier: Programming Language :: Python
Classifier: Topic :: Internet :: WWW/HTTP :: Indexing/Search
